MANIFEST.in
README.md
setup.py
astakosclient/__init__.py
astakosclient/errors.py
astakosclient/tests.py
astakosclient/utils.py
astakosclient/version.py
astakosclient.egg-info/PKG-INFO
astakosclient.egg-info/SOURCES.txt
astakosclient.egg-info/dependency_links.txt
astakosclient.egg-info/not-zip-safe
astakosclient.egg-info/requires.txt
astakosclient.egg-info/top_level.txt